LICENSE
MANIFEST.in
README.md
setup.py
scripts/yup
yup/__init__.py
yup/_version.py
yup/document.py
yup/render.py
yup.egg-info/PKG-INFO
yup.egg-info/SOURCES.txt
yup.egg-info/dependency_links.txt
yup.egg-info/not-zip-safe
yup.egg-info/requires.txt
yup.egg-info/top_level.txt
yup/data/template.html
yup/data/css/docs.css
yup/data/css/github.css
yup/data/css/normalize.css
yup/data/css/fonts/aller-bold.eot
yup/data/css/fonts/aller-bold.ttf
yup/data/css/fonts/aller-bold.woff
yup/data/css/fonts/aller-light.eot
yup/data/css/fonts/aller-light.ttf
yup/data/css/fonts/aller-light.woff
yup/data/css/fonts/novecento-bold.eot
yup/data/css/fonts/novecento-bold.ttf
yup/data/css/fonts/novecento-bold.woff