Metadata-Version: 1.1
Name: yup
Version: 0.1.0
Summary: Generate REST API documentation from YAML files
Home-page: https://github.com/noonat/yup
Author: Nathan Ostgard
Author-email: no@nathanostgard.com
License: Apache License, Version 2.0
Platform: UNKNOWN
Classifier: Development Status :: 4 - Beta
Classifier: Intended Audience :: Developers
Classifier: Operating System :: OS Independent
Classifier: Programming Language :: Python
Classifier: Programming Language :: Python :: 2.7
Classifier: Topic :: Internet
Classifier: Topic :: Software Development :: Libraries :: Python Modules
Classifier: License :: OSI Approved :: MIT License
